<?xml version="1.0" encoding="UTF-8"?>
<FFSignatureFile xmlns="http://www.nationalarchives.gov.uk/pronom/SignatureFile" Version="1" DateCreated="2022-11-16T16:48:25+00:00">
  <InternalSignatureCollection>
  <InternalSignature ID="1" Specificity="Specific">
  <ByteSequence Reference="BOFoffset">
    <SubSequence MinFragLength="0" Position="1" SubSeqMaxOffset="0" SubSeqMinOffset="0">
      <Sequence>014000C8</Sequence>
      <DefaultShift>5</DefaultShift>
      <Shift Byte="01">4</Shift>
      <Shift Byte="40">3</Shift>
      <Shift Byte="00">2</Shift>
      <Shift Byte="C8">1</Shift>
    </SubSequence>
  </ByteSequence>
  <ByteSequence Reference="BOFoffset">
    <SubSequence MinFragLength="0" Position="1" SubSeqMaxOffset="8" SubSeqMinOffset="8">
      <Sequence>2800</Sequence>
      <DefaultShift>3</DefaultShift>
      <Shift Byte="28">2</Shift>
      <Shift Byte="00">1</Shift>
    </SubSequence>
  </ByteSequence>
</InternalSignature>
</InternalSignatureCollection>
<FileFormatCollection>
  <FileFormat ID="1" Name="PhotoChrome Raster Image" PUID="dev/1" Version="1.0" MIMEType="application/octet-stream">
    <InternalSignatureID>1</InternalSignatureID>
    <Extension>pcs</Extension>
    <HasPriorityOverFileFormatID>687</HasPriorityOverFileFormatID>
  </FileFormat>
</FileFormatCollection></FFSignatureFile>
