<?xml version="1.0" encoding="UTF-8"?>
<FFSignatureFile xmlns="http://www.nationalarchives.gov.uk/pronom/SignatureFile" Version="1" DateCreated="2022-04-22T12:06:08+00:00">
  <InternalSignatureCollection>
  <InternalSignature ID="1" Specificity="Specific">
  <ByteSequence Reference="BOFoffset">
    <SubSequence MinFragLength="0" Position="1" SubSeqMaxOffset="0" SubSeqMinOffset="0">
      <Sequence>4A534A2053494E544143</Sequence>
      <DefaultShift>11</DefaultShift>
      <Shift Byte="4A">8</Shift>
      <Shift Byte="53">6</Shift>
      <Shift Byte="20">7</Shift>
      <Shift Byte="49">5</Shift>
      <Shift Byte="4E">4</Shift>
      <Shift Byte="54">3</Shift>
      <Shift Byte="41">2</Shift>
      <Shift Byte="43">1</Shift>
    </SubSequence>
  </ByteSequence>
</InternalSignature>
</InternalSignatureCollection>
<FileFormatCollection>
  <FileFormat ID="1" Name="SINTAC Interactive Fiction Font File" PUID="dev/1" Version="1.0" MIMEType="application/octet-stream">
    <InternalSignatureID>1</InternalSignatureID>
    <Extension>fnt</Extension>
  </FileFormat>
</FileFormatCollection></FFSignatureFile>
