<?xml version="1.0" encoding="UTF-8"?>
<FFSignatureFile xmlns="http://www.nationalarchives.gov.uk/pronom/SignatureFile" Version="1" DateCreated="2022-05-03T13:05:42+00:00">
  <InternalSignatureCollection>
  <InternalSignature ID="1" Specificity="Specific">
  <ByteSequence Reference="BOFoffset">
    <SubSequence MinFragLength="0" Position="1" SubSeqMaxOffset="0" SubSeqMinOffset="0">
      <Sequence>47444157</Sequence>
      <DefaultShift>5</DefaultShift>
      <Shift Byte="47">4</Shift>
      <Shift Byte="44">3</Shift>
      <Shift Byte="41">2</Shift>
      <Shift Byte="57">1</Shift>
    </SubSequence>
  </ByteSequence>
  <ByteSequence Reference="BOFoffset">
    <SubSequence MinFragLength="0" Position="1" SubSeqMaxOffset="8" SubSeqMinOffset="8">
      <Sequence>56455253</Sequence>
      <DefaultShift>5</DefaultShift>
      <Shift Byte="56">4</Shift>
      <Shift Byte="45">3</Shift>
      <Shift Byte="52">2</Shift>
      <Shift Byte="53">1</Shift>
    </SubSequence>
  </ByteSequence>
</InternalSignature>
</InternalSignatureCollection>
<FileFormatCollection>
  <FileFormat ID="1" Name="Gold Disk Animation AWM Format" PUID="dev/1" Version="1.0" MIMEType="application/octet-stream">
    <InternalSignatureID>1</InternalSignatureID>
    <Extension>awm</Extension>
  </FileFormat>
</FileFormatCollection></FFSignatureFile>
