<?xml version="1.0" encoding="UTF-8"?>
<FFSignatureFile xmlns="http://www.nationalarchives.gov.uk/pronom/SignatureFile" Version="1" DateCreated="2020-09-14T14:47:56+01:00">
  <InternalSignatureCollection>
  <InternalSignature ID="1" Specificity="Specific">
  <ByteSequence Reference="BOFoffset">
    <SubSequence MinFragLength="0" Position="1" SubSeqMaxOffset="0" SubSeqMinOffset="0">
      <Sequence>4E53494630312E30</Sequence>
      <DefaultShift>9</DefaultShift>
      <Shift Byte="4E">8</Shift>
      <Shift Byte="53">7</Shift>
      <Shift Byte="49">6</Shift>
      <Shift Byte="46">5</Shift>
      <Shift Byte="30">1</Shift>
      <Shift Byte="31">3</Shift>
      <Shift Byte="2E">2</Shift>
    </SubSequence>
  </ByteSequence>
</InternalSignature>
</InternalSignatureCollection>
<FileFormatCollection>
  <FileFormat ID="1" Name="NATO Secondary Imagery Format" PUID="dev/1" Version="1.0" MIMEType="application/octet-stream">
    <InternalSignatureID>1</InternalSignatureID>
    <Extension>nsf</Extension>
  </FileFormat>
</FileFormatCollection></FFSignatureFile>
