<?xml version="1.0" encoding="UTF-8"?>
<FFSignatureFile xmlns="http://www.nationalarchives.gov.uk/pronom/SignatureFile" Version="1" DateCreated="2022-05-06T13:01:09+00:00">
  <InternalSignatureCollection>
  <InternalSignature ID="1" Specificity="Specific">
  <ByteSequence Reference="BOFoffset">
    <SubSequence MinFragLength="0" Position="1" SubSeqMaxOffset="0" SubSeqMinOffset="0">
      <Sequence>46318F0001008F0043322E33</Sequence>
      <DefaultShift>13</DefaultShift>
      <Shift Byte="46">12</Shift>
      <Shift Byte="31">11</Shift>
      <Shift Byte="8F">6</Shift>
      <Shift Byte="00">5</Shift>
      <Shift Byte="01">8</Shift>
      <Shift Byte="43">4</Shift>
      <Shift Byte="32">3</Shift>
      <Shift Byte="2E">2</Shift>
      <Shift Byte="33">1</Shift>
    </SubSequence>
  </ByteSequence>
</InternalSignature>
</InternalSignatureCollection>
<FileFormatCollection>
  <FileFormat ID="1" Name="Bitstream Compressed Outline Font" PUID="dev/1" Version="1.0" MIMEType="application/octet-stream">
    <InternalSignatureID>1</InternalSignatureID>
    <Extension>bco</Extension>
  </FileFormat>
</FileFormatCollection></FFSignatureFile>
