<?xml version="1.0" encoding="UTF-8"?>
<FFSignatureFile xmlns="http://www.nationalarchives.gov.uk/pronom/SignatureFile" Version="1" DateCreated="2021-12-14T14:59:51+00:00">
  <InternalSignatureCollection>
  <InternalSignature ID="1" Specificity="Specific">
  <ByteSequence Reference="BOFoffset">
    <SubSequence MinFragLength="0" Position="1" SubSeqMaxOffset="0" SubSeqMinOffset="0">
      <Sequence>43666631BC9999CE4000</Sequence>
      <DefaultShift>11</DefaultShift>
      <Shift Byte="43">10</Shift>
      <Shift Byte="66">8</Shift>
      <Shift Byte="31">7</Shift>
      <Shift Byte="BC">6</Shift>
      <Shift Byte="99">4</Shift>
      <Shift Byte="CE">3</Shift>
      <Shift Byte="40">2</Shift>
      <Shift Byte="00">1</Shift>
    </SubSequence>
  </ByteSequence>
</InternalSignature>
</InternalSignatureCollection>
<FileFormatCollection>
  <FileFormat ID="1" Name="Fontographer Font Format" PUID="dev/1" Version="1.0" MIMEType="application/octet-stream">
    <InternalSignatureID>1</InternalSignatureID>
    <Extension>fog</Extension>
  </FileFormat>
</FileFormatCollection></FFSignatureFile>
