<?xml version="1.0" encoding="UTF-8"?>
<FFSignatureFile xmlns="http://www.nationalarchives.gov.uk/pronom/SignatureFile" Version="1" DateCreated="2022-05-23T11:49:02+00:00">
  <InternalSignatureCollection>
  <InternalSignature ID="1" Specificity="Specific">
  <ByteSequence Reference="BOFoffset">
    <SubSequence MinFragLength="0" Position="1" SubSeqMaxOffset="0" SubSeqMinOffset="0">
      <Sequence>3B43726561746564206279204175746F434144</Sequence>
      <DefaultShift>20</DefaultShift>
      <Shift Byte="3B">19</Shift>
      <Shift Byte="43">3</Shift>
      <Shift Byte="72">17</Shift>
      <Shift Byte="65">13</Shift>
      <Shift Byte="61">15</Shift>
      <Shift Byte="74">5</Shift>
      <Shift Byte="64">12</Shift>
      <Shift Byte="20">8</Shift>
      <Shift Byte="62">10</Shift>
      <Shift Byte="79">9</Shift>
      <Shift Byte="41">2</Shift>
      <Shift Byte="75">6</Shift>
      <Shift Byte="6F">4</Shift>
      <Shift Byte="44">1</Shift>
    </SubSequence>
  </ByteSequence>
  <ByteSequence>
    <SubSequence MinFragLength="0" Position="1" SubSeqMinOffset="0">
      <Sequence>50454E5F5749445448</Sequence>
      <DefaultShift>10</DefaultShift>
      <Shift Byte="50">9</Shift>
      <Shift Byte="45">8</Shift>
      <Shift Byte="4E">7</Shift>
      <Shift Byte="5F">6</Shift>
      <Shift Byte="57">5</Shift>
      <Shift Byte="49">4</Shift>
      <Shift Byte="44">3</Shift>
      <Shift Byte="54">2</Shift>
      <Shift Byte="48">1</Shift>
    </SubSequence>
  </ByteSequence>
  <ByteSequence>
    <SubSequence MinFragLength="0" Position="1" SubSeqMinOffset="0">
      <Sequence>504C4F545F46494C45</Sequence>
      <DefaultShift>10</DefaultShift>
      <Shift Byte="50">9</Shift>
      <Shift Byte="4C">2</Shift>
      <Shift Byte="4F">7</Shift>
      <Shift Byte="54">6</Shift>
      <Shift Byte="5F">5</Shift>
      <Shift Byte="46">4</Shift>
      <Shift Byte="49">3</Shift>
      <Shift Byte="45">1</Shift>
    </SubSequence>
  </ByteSequence>
</InternalSignature>
</InternalSignatureCollection>
<FileFormatCollection>
  <FileFormat ID="1" Name="AutoCAD Plot Configuration File (R13)" PUID="x-fmt/79" Version="1.0" MIMEType="text/plain">
    <InternalSignatureID>1</InternalSignatureID>
    <Extension>pcp</Extension>
  </FileFormat>
</FileFormatCollection></FFSignatureFile>
