<?xml version="1.0" encoding="UTF-8"?>
<FFSignatureFile xmlns="http://www.nationalarchives.gov.uk/pronom/SignatureFile" Version="1" DateCreated="2021-12-06T19:58:07+00:00">
  <InternalSignatureCollection>
  <InternalSignature ID="1" Specificity="Specific">
  <ByteSequence Reference="BOFoffset">
    <SubSequence MinFragLength="0" Position="1" SubSeqMaxOffset="0" SubSeqMinOffset="0">
      <Sequence>1290A87F000000000001722A013E000005000202326E6F4B</Sequence>
      <DefaultShift>25</DefaultShift>
      <Shift Byte="12">24</Shift>
      <Shift Byte="90">23</Shift>
      <Shift Byte="A8">22</Shift>
      <Shift Byte="7F">21</Shift>
      <Shift Byte="00">7</Shift>
      <Shift Byte="01">12</Shift>
      <Shift Byte="72">14</Shift>
      <Shift Byte="2A">13</Shift>
      <Shift Byte="3E">11</Shift>
      <Shift Byte="05">8</Shift>
      <Shift Byte="02">5</Shift>
      <Shift Byte="32">4</Shift>
      <Shift Byte="6E">3</Shift>
      <Shift Byte="6F">2</Shift>
      <Shift Byte="4B">1</Shift>
    </SubSequence>
  </ByteSequence>
</InternalSignature>
</InternalSignatureCollection>
<FileFormatCollection>
  <FileFormat ID="1" Name="Kontakt Multi Instrument File" PUID="dev/1" Version="1.0" MIMEType="application/octet-stream">
    <InternalSignatureID>1</InternalSignatureID>
    <Extension>nkm</Extension>
  </FileFormat>
</FileFormatCollection></FFSignatureFile>
