<?xml version="1.0" encoding="UTF-8"?>
<FFSignatureFile xmlns="http://www.nationalarchives.gov.uk/pronom/SignatureFile" Version="1" DateCreated="2020-08-31T12:22:57+01:00">
  <InternalSignatureCollection>
  <InternalSignature ID="1" Specificity="Specific">
  <ByteSequence Reference="BOFoffset">
    <SubSequence MinFragLength="0" Position="1" SubSeqMaxOffset="0" SubSeqMinOffset="0">
      <Sequence>534E4400</Sequence>
      <DefaultShift>5</DefaultShift>
      <Shift Byte="53">4</Shift>
      <Shift Byte="4E">3</Shift>
      <Shift Byte="44">2</Shift>
      <Shift Byte="00">1</Shift>
    </SubSequence>
  </ByteSequence>
</InternalSignature>
</InternalSignatureCollection>
<FileFormatCollection>
  <FileFormat ID="1" Name="Inverse Frequency Sound Format" PUID="dev/1" Version="1.0" MIMEType="application/octet-stream">
    <InternalSignatureID>1</InternalSignatureID>
    <Extension/>
  </FileFormat>
</FileFormatCollection></FFSignatureFile>
