<?xml version="1.0" encoding="UTF-8"?>
<FFSignatureFile xmlns="http://www.nationalarchives.gov.uk/pronom/SignatureFile" Version="1" DateCreated="2021-05-18T11:31:57+00:00">
  <InternalSignatureCollection>
  <InternalSignature ID="1" Specificity="Specific">
  <ByteSequence Reference="BOFoffset">
    <SubSequence MinFragLength="0" Position="1" SubSeqMaxOffset="0" SubSeqMinOffset="0">
      <Sequence>3C3F786D6C2076657273696F6E3D22312E3022</Sequence>
      <DefaultShift>20</DefaultShift>
      <Shift Byte="3C">19</Shift>
      <Shift Byte="3F">18</Shift>
      <Shift Byte="78">17</Shift>
      <Shift Byte="6D">16</Shift>
      <Shift Byte="6C">15</Shift>
      <Shift Byte="20">14</Shift>
      <Shift Byte="76">13</Shift>
      <Shift Byte="65">12</Shift>
      <Shift Byte="72">11</Shift>
      <Shift Byte="73">10</Shift>
      <Shift Byte="69">9</Shift>
      <Shift Byte="6F">8</Shift>
      <Shift Byte="6E">7</Shift>
      <Shift Byte="3D">6</Shift>
      <Shift Byte="22">1</Shift>
      <Shift Byte="31">4</Shift>
      <Shift Byte="2E">3</Shift>
      <Shift Byte="30">2</Shift>
    </SubSequence>
  </ByteSequence>
  <ByteSequence>
    <SubSequence MinFragLength="0" Position="1" SubSeqMinOffset="0">
      <Sequence>3C6D7A4D4C20786D6C6E733D22687474703A2F2F</Sequence>
      <DefaultShift>21</DefaultShift>
      <Shift Byte="3C">20</Shift>
      <Shift Byte="6D">13</Shift>
      <Shift Byte="7A">18</Shift>
      <Shift Byte="4D">17</Shift>
      <Shift Byte="4C">16</Shift>
      <Shift Byte="20">15</Shift>
      <Shift Byte="78">14</Shift>
      <Shift Byte="6C">12</Shift>
      <Shift Byte="6E">11</Shift>
      <Shift Byte="73">10</Shift>
      <Shift Byte="3D">9</Shift>
      <Shift Byte="22">8</Shift>
      <Shift Byte="68">7</Shift>
      <Shift Byte="74">5</Shift>
      <Shift Byte="70">4</Shift>
      <Shift Byte="3A">3</Shift>
      <Shift Byte="2F">1</Shift>
    </SubSequence>
  </ByteSequence>
</InternalSignature>
</InternalSignatureCollection>
<FileFormatCollection>
  <FileFormat ID="1" Name="mzML File" PUID="dev/1" Version="1.0" MIMEType="text/xml">
    <InternalSignatureID>1</InternalSignatureID>
    <Extension>mzml</Extension>
    <HasPriorityOverFileFormatID>638</HasPriorityOverFileFormatID>
  </FileFormat>
</FileFormatCollection></FFSignatureFile>
