<?xml version="1.0" encoding="UTF-8"?>
<FFSignatureFile xmlns="http://www.nationalarchives.gov.uk/pronom/SignatureFile" Version="1" DateCreated="2023-07-20T16:00:28+00:00">
  <InternalSignatureCollection>
  <InternalSignature ID="1" Specificity="Specific">
  <ByteSequence Reference="BOFoffset">
    <SubSequence MinFragLength="0" Position="1" SubSeqMaxOffset="0" SubSeqMinOffset="0">
      <Sequence>D36C0000</Sequence>
      <DefaultShift>5</DefaultShift>
      <Shift Byte="D3">4</Shift>
      <Shift Byte="6C">3</Shift>
      <Shift Byte="00">1</Shift>
      <RightFragment MaxOffset="0" MinOffset="0" Position="1">00</RightFragment>
      <RightFragment MaxOffset="0" MinOffset="0" Position="1">06</RightFragment>
      <RightFragment MaxOffset="0" MinOffset="0" Position="2">00000000</RightFragment>
      <RightFragment MaxOffset="0" MinOffset="0" Position="3">08</RightFragment>
      <RightFragment MaxOffset="0" MinOffset="0" Position="3">20</RightFragment>
      <RightFragment MaxOffset="0" MinOffset="0" Position="4">0000</RightFragment>
      <RightFragment MaxOffset="0" MinOffset="0" Position="5">01</RightFragment>
      <RightFragment MaxOffset="0" MinOffset="0" Position="5">02</RightFragment>
      <RightFragment MaxOffset="0" MinOffset="0" Position="5">03</RightFragment>
      <RightFragment MaxOffset="0" MinOffset="0" Position="5">06</RightFragment>
    </SubSequence>
  </ByteSequence>
</InternalSignature>
</InternalSignatureCollection>
<FileFormatCollection>
  <FileFormat ID="1" Name="VLF Receiver Software Toolkit VT Format" PUID="dev/1" Version="1.0" MIMEType="application/octet-stream">
    <InternalSignatureID>1</InternalSignatureID>
    <Extension>vt</Extension>
  </FileFormat>
</FileFormatCollection></FFSignatureFile>
