<?xml version="1.0" encoding="UTF-8"?>
<FFSignatureFile xmlns="http://www.nationalarchives.gov.uk/pronom/SignatureFile" Version="1" DateCreated="2022-03-10T12:40:45+00:00">
  <InternalSignatureCollection>
  <InternalSignature ID="1" Specificity="Specific">
  <ByteSequence Reference="BOFoffset">
    <SubSequence MinFragLength="0" Position="1" SubSeqMaxOffset="0" SubSeqMinOffset="0">
      <Sequence>302046494C45</Sequence>
      <DefaultShift>7</DefaultShift>
      <Shift Byte="30">6</Shift>
      <Shift Byte="20">5</Shift>
      <Shift Byte="46">4</Shift>
      <Shift Byte="49">3</Shift>
      <Shift Byte="4C">2</Shift>
      <Shift Byte="45">1</Shift>
    </SubSequence>
  </ByteSequence>
</InternalSignature>
</InternalSignatureCollection>
<FileFormatCollection>
  <FileFormat ID="1" Name="LDraw File Format" PUID="dev/1" Version="1.0" MIMEType="text/plain">
    <InternalSignatureID>1</InternalSignatureID>
    <Extension>mpd</Extension>
  </FileFormat>
</FileFormatCollection></FFSignatureFile>
