<?xml version="1.0" encoding="UTF-8"?>
<FFSignatureFile xmlns="http://www.nationalarchives.gov.uk/pronom/SignatureFile" Version="1" DateCreated="2020-08-07T13:05:57+01:00">
  <InternalSignatureCollection>
  <InternalSignature ID="1" Specificity="Specific">
  <ByteSequence Reference="BOFoffset">
    <SubSequence MinFragLength="0" Position="1" SubSeqMaxOffset="0" SubSeqMinOffset="0">
      <Sequence>00044E4E54524B4D5A58</Sequence>
      <DefaultShift>11</DefaultShift>
      <Shift Byte="00">10</Shift>
      <Shift Byte="04">9</Shift>
      <Shift Byte="4E">7</Shift>
      <Shift Byte="54">6</Shift>
      <Shift Byte="52">5</Shift>
      <Shift Byte="4B">4</Shift>
      <Shift Byte="4D">3</Shift>
      <Shift Byte="5A">2</Shift>
      <Shift Byte="58">1</Shift>
    </SubSequence>
  </ByteSequence>
</InternalSignature>
</InternalSignatureCollection>
<FileFormatCollection>
  <FileFormat ID="1" Name="CyberTracker 64 chiptune" PUID="dev/1" Version="1.0" MIMEType="application/octet-stream">
    <InternalSignatureID>1</InternalSignatureID>
    <Extension>ct</Extension>
  </FileFormat>
</FileFormatCollection></FFSignatureFile>
